osrm/__init__.py
osrm/engine/__init__.py
osrm/engine/contraction_hierarchies.py
osrm/engine/dijkstra.py
osrm/extractor/__init__.py
osrm/extractor/graph_builder.py
osrm/extractor/parser.py
osrm/extractor/pbf_parser.py
osrm/server/__init__.py
osrm/server/api.py
osrm/structures/__init__.py
osrm/structures/graph.py
py_osrm_backend-0.1.1.dist-info/licenses/LICENSE
py_osrm_backend-0.1.1.dist-info/METADATA
py_osrm_backend-0.1.1.dist-info/WHEEL
py_osrm_backend-0.1.1.dist-info/top_level.txt
py_osrm_backend-0.1.1.dist-info/RECORD
