Metadata-Version: 2.4
Name: py-osrm-backend
Version: 0.1.1
Summary: A Python implementation of OSRM backend core functionality
Home-page: https://github.com/GalTechDev/py-osrm-backend
Author: GalTechDev
License: MIT
Project-URL: Homepage, https://github.com/GalTechDev/py-osrm-backend
Project-URL: Repository, https://github.com/GalTechDev/py-osrm-backend
Project-URL: Issues, https://github.com/GalTechDev/py-osrm-backend/issues
Keywords: osrm,routing,osm,openstreetmap,dijkstra,navigation
Classifier: Development Status :: 3 - Alpha
Classifier: Intended Audience :: Developers
Classifier: License :: OSI Approved :: MIT License
Classifier: Programming Language :: Python :: 3
Classifier: Programming Language :: Python :: 3.8
Classifier: Programming Language :: Python :: 3.9
Classifier: Programming Language :: Python :: 3.10
Classifier: Programming Language :: Python :: 3.11
Classifier: Programming Language :: Python :: 3.12
Classifier: Topic :: Scientific/Engineering :: GIS
Classifier: Topic :: Software Development :: Libraries :: Python Modules
Requires-Python: >=3.8
License-File: LICENSE
Requires-Dist: flask
Requires-Dist: osmium
Provides-Extra: dev
Requires-Dist: pytest; extra == "dev"
Requires-Dist: build; extra == "dev"
Requires-Dist: twine; extra == "dev"
Dynamic: home-page
Dynamic: license-file
Dynamic: requires-python
